.gitignore
LICENSE
README.md
setup.cfg
setup.py
docs/conf.py
docs/index.rst
docs/make.bat
docs/_sources/index.txt
docs/_static/ajax-loader.gif
docs/_static/basic.css
docs/_static/comment-bright.png
docs/_static/comment-close.png
docs/_static/comment.png
docs/_static/default.css
docs/_static/doctools.js
docs/_static/down-pressed.png
docs/_static/down.png
docs/_static/file.png
docs/_static/jquery.js
docs/_static/minus.png
docs/_static/plus.png
docs/_static/pygments.css
docs/_static/searchtools.js
docs/_static/sidebar.js
docs/_static/underscore.js
docs/_static/up-pressed.png
docs/_static/up.png
docs/_static/websupport.js
examples/alphaisyn.mod
examples/binzegger_connectivity_table.json
examples/brunel_alpha_nest.py
examples/example_brunel.py
examples/example_microcircuit.py
examples/example_microcircuit_params.py
examples/example_plotting.py
examples/expsyni.mod
examples/microcircuit.sli
examples/morphologies/ex.hoc
examples/morphologies/in.hoc
examples/morphologies/ballnsticks/L23E_p23.hoc
examples/morphologies/ballnsticks/L23I_b23.hoc
examples/morphologies/ballnsticks/L23I_nb23.hoc
examples/morphologies/ballnsticks/L4E_p4.hoc
examples/morphologies/ballnsticks/L4E_ss4(L23).hoc
examples/morphologies/ballnsticks/L4E_ss4(L4).hoc
examples/morphologies/ballnsticks/L4I_b4.hoc
examples/morphologies/ballnsticks/L4I_nb4.hoc
examples/morphologies/ballnsticks/L5E_p5(L23).hoc
examples/morphologies/ballnsticks/L5E_p5(L56).hoc
examples/morphologies/ballnsticks/L5I_b5.hoc
examples/morphologies/ballnsticks/L5I_nb5.hoc
examples/morphologies/ballnsticks/L6E_p6(L4).hoc
examples/morphologies/ballnsticks/L6E_p6(L56).hoc
examples/morphologies/ballnsticks/L6I_b6.hoc
examples/morphologies/ballnsticks/L6I_nb6.hoc
examples/morphologies/ballnsticks/withapic.hoc
examples/morphologies/ballnsticks/withoutapic.hoc
hybridLFPy/__init__.py
hybridLFPy/cachednetworks.py
hybridLFPy/csd.py
hybridLFPy/gdf.py
hybridLFPy/helpers.py
hybridLFPy/population.py
hybridLFPy/postproc.py
hybridLFPy/testing.py
hybridLFPy.egg-info/PKG-INFO
hybridLFPy.egg-info/SOURCES.txt
hybridLFPy.egg-info/dependency_links.txt
hybridLFPy.egg-info/requires.txt
hybridLFPy.egg-info/top_level.txt
