Metadata-Version: 1.1
Name: hybridLFPy
Version: 0.1.2
Summary: methods to calculate LFPs with spike events from network sim
Home-page: https://github.com/INM-6/hybridLFPy
Author: Espen Hagen
Author-email: e.hagen@fz-juelich.de
License: LICENSE
Download-URL: https://github.com/INM-6/hybridLFPy/tarball/v0.1.2
Platform: UNKNOWN
Classifier: License :: OSI Approved :: GNU General Public License (GPL)
Classifier: Programming Language :: Python
Classifier: Programming Language :: Python :: 2.6
Classifier: Programming Language :: Python :: 2.7
Classifier: Programming Language :: Python :: 3.3
Classifier: Programming Language :: Cython
Classifier: Operating System :: OS Independent
Classifier: Topic :: Scientific/Engineering
Classifier: Topic :: Scientific/Engineering :: Physics
Classifier: Intended Audience :: Developers
Classifier: Intended Audience :: Science/Research
Classifier: Development Status :: 4 - Beta
Provides: hybridLFPy
